EFL/__init__.py
EFL/aggregators/aggregator.py
EFL/aggregators/distances.py
EFL/aggregators/fedopt_aggregator.py
EFL/aggregators/temperature.py
EFL/data_structures/cluster_sturcutre.py
EFL/files/archive.py
EFL/files/handlers.py
EFL/files/loggers.py
EFL/model/federated_model.py
EFL/node/federated_node.py
EFL/operations/evaluations.py
EFL/operations/orchestrations.py
EFL/simulation/simulation.py
EFL/utils/animation.py
EFL/utils/computations.py
EFL/utils/select_gradients.py
EFL/utils/splitters.py
clustered_fl-0.1.0.dist-info/LICENSE
clustered_fl-0.1.0.dist-info/METADATA
clustered_fl-0.1.0.dist-info/WHEEL
clustered_fl-0.1.0.dist-info/RECORD
